aemeasure/__init__.py
aemeasure/context_printer.py
aemeasure/measurement.py
aemeasure/evaluation_tools/__init__.py
aemeasure/evaluation_tools/interval_tables.py
aemeasure/evaluation_tools/multiplex.py
aemeasure/plotting/__init__.py
aemeasure/plotting/escape_latex.py
aemeasure/plotting/interval_tables.py
aemeasure/plotting/quick_setup.py
aemeasure/utils/__init__.py
aemeasure/utils/capture.py
aemeasure/utils/git.py
aemeasure-0.0.20.dist-info/METADATA
aemeasure-0.0.20.dist-info/WHEEL
aemeasure-0.0.20.dist-info/top_level.txt
aemeasure-0.0.20.dist-info/RECORD
