Metadata-Version: 2.1
Name: aemeasure
Version: 0.0.20
Summary: Simple tools for logging experiments in algorithm engineering
Home-page: https://gitlab.ibr.cs.tu-bs.de/alg/aemeasure
Author: TU Braunschweig, IBR, Algorithms Group (Dominik Krupke)
Author-email: krupke@ibr.cs.tu-bs.de
License: UNKNOWN
Platform: UNKNOWN
Classifier: Programming Language :: Python :: 3
Classifier: License :: OSI Approved :: MIT License
Classifier: Development Status :: 1 - Planning
Requires-Python: >=3.6
Requires-Dist: pandas
